mytestprojfrompoetry/__init__.py
mytestprojfrompoetry-0.1.0.dist-info/WHEEL
mytestprojfrompoetry-0.1.0.dist-info/METADATA
mytestprojfrompoetry-0.1.0.dist-info/RECORD
