Metadata-Version: 2.1
Name: mytestprojfrompoetry
Version: 0.1.0
Summary: 
Author: Your Name
Author-email: you@example.com
Requires-Python: >=3.7,<4.0
Classifier: Programming Language :: Python :: 3
Classifier: Programming Language :: Python :: 3.7
Classifier: Programming Language :: Python :: 3.8
Requires-Dist: geopandas (>=0.7.0,<0.8.0)
Requires-Dist: pandas (>=1.0.3,<2.0.0)
